[
    {
        "class": "Upper lip",
        "polygon": [
            [
                331,
                532
            ],
            [
                363,
                526
            ],
            [
                406,
                523
            ],
            [
                463,
                536
            ],
            [
                438,
                543
            ],
            [
                359,
                543
            ]
        ]
    },
    {
        "class": "Nasal region",
        "polygon": [
            [
                345,
                501
            ],
            [
                370,
                511
            ],
            [
                423,
                512
            ],
            [
                435,
                511
            ],
            [
                438,
                492
            ],
            [
                417,
                471
            ],
            [
                411,
                415
            ],
            [
                391,
                395
            ],
            [
                362,
                428
            ],
            [
                351,
                471
            ],
            [
                341,
                483
            ]
        ]
    },
    {
        "class": "Border(lip region)",
        "polygon": [
            [
                327,
                562
            ],
            [
                335,
                578
            ],
            [
                380,
                591
            ],
            [
                421,
                589
            ],
            [
                464,
                571
            ],
            [
                483,
                558
            ],
            [
                432,
                551
            ],
            [
                401,
                553
            ],
            [
                359,
                549
            ],
            [
                341,
                555
            ]
        ]
    },
    {
        "class": "Mental region(chin)",
        "polygon": [
            [
                325,
                581
            ],
            [
                375,
                607
            ],
            [
                422,
                604
            ],
            [
                483,
                579
            ],
            [
                446,
                647
            ],
            [
                358,
                652
            ]
        ]
    },
    {
        "class": "Left Side Frontal",
        "polygon": [
            [
                431,
                356
            ],
            [
                484,
                345
            ],
            [
                539,
                352
            ],
            [
                508,
                278
            ],
            [
                459,
                253
            ],
            [
                429,
                254
            ]
        ]
    },
    {
        "class": "Right Side Frontal",
        "polygon": [
            [
                343,
                363
            ],
            [
                303,
                351
            ],
            [
                289,
                348
            ],
            [
                296,
                301
            ],
            [
                307,
                262
            ],
            [
                350,
                256
            ]
        ]
    },
    {
        "class": "Central Frontal region",
        "polygon": [
            [
                359,
                367
            ],
            [
                419,
                359
            ],
            [
                415,
                244
            ],
            [
                365,
                249
            ]
        ]
    },
    {
        "class": "Upper eyelid",
        "polygon": [
            [
                443,
                400
            ],
            [
                467,
                392
            ],
            [
                502,
                387
            ],
            [
                538,
                404
            ],
            [
                556,
                397
            ],
            [
                522,
                371
            ],
            [
                484,
                373
            ],
            [
                445,
                387
            ]
        ]
    },
    {
        "class": "Upper eyelid",
        "polygon": [
            [
                331,
                395
            ],
            [
                303,
                388
            ],
            [
                290,
                388
            ],
            [
                279,
                375
            ],
            [
                302,
                379
            ],
            [
                335,
                387
            ]
        ]
    },
    {
        "class": "Left Lateral Canthus",
        "polygon": [
            [
                491,
                423
            ],
            [
                526,
                419
            ],
            [
                527,
                436
            ],
            [
                488,
                443
            ]
        ]
    },
    {
        "class": "Left Medial Canthus",
        "polygon": [
            [
                446,
                422
            ],
            [
                486,
                424
            ],
            [
                481,
                439
            ],
            [
                451,
                439
            ]
        ]
    },
    {
        "class": "Right Medial Canthus",
        "polygon": [
            [
                316,
                421
            ],
            [
                352,
                420
            ],
            [
                349,
                437
            ],
            [
                324,
                438
            ]
        ]
    },
    {
        "class": "Right Lateral Canthus",
        "polygon": [
            [
                294,
                415
            ],
            [
                307,
                418
            ],
            [
                315,
                437
            ],
            [
                296,
                437
            ],
            [
                295,
                435
            ]
        ]
    },
    {
        "class": "Upper Cheek",
        "polygon": [
            [
                485,
                509
            ],
            [
                559,
                492
            ],
            [
                568,
                436
            ],
            [
                448,
                450
            ]
        ]
    },
    {
        "class": "Lower Cheek",
        "polygon": [
            [
                490,
                519
            ],
            [
                559,
                505
            ],
            [
                549,
                543
            ],
            [
                504,
                543
            ]
        ]
    }
]