[
    {
        "class": "Upper lip",
        "polygon": [
            [
                346,
                537
            ],
            [
                379,
                526
            ],
            [
                407,
                526
            ],
            [
                463,
                542
            ],
            [
                448,
                510
            ],
            [
                405,
                506
            ],
            [
                350,
                512
            ]
        ]
    },
    {
        "class": "Nasal region",
        "polygon": [
            [
                359,
                477
            ],
            [
                391,
                474
            ],
            [
                406,
                479
            ],
            [
                432,
                477
            ],
            [
                448,
                490
            ],
            [
                429,
                435
            ],
            [
                412,
                380
            ],
            [
                382,
                389
            ],
            [
                377,
                426
            ],
            [
                361,
                458
            ]
        ]
    },
    {
        "class": "Left Side Frontal",
        "polygon": [
            [
                456,
                349
            ],
            [
                454,
                287
            ],
            [
                487,
                280
            ],
            [
                525,
                349
            ]
        ]
    },
    {
        "class": "Right Side Frontal",
        "polygon": [
            [
                368,
                359
            ],
            [
                364,
                289
            ],
            [
                331,
                290
            ],
            [
                283,
                330
            ],
            [
                291,
                347
            ]
        ]
    },
    {
        "class": "Central Frontal region",
        "polygon": [
            [
                380,
                359
            ],
            [
                383,
                302
            ],
            [
                410,
                275
            ],
            [
                435,
                294
            ],
            [
                444,
                336
            ]
        ]
    },
    {
        "class": "Upper eyelid",
        "polygon": [
            [
                250,
                397
            ],
            [
                270,
                397
            ],
            [
                300,
                393
            ],
            [
                352,
                395
            ],
            [
                339,
                379
            ],
            [
                294,
                379
            ],
            [
                273,
                379
            ]
        ]
    },
    {
        "class": "Upper eyelid",
        "polygon": [
            [
                452,
                398
            ],
            [
                483,
                391
            ],
            [
                525,
                398
            ],
            [
                531,
                377
            ],
            [
                500,
                376
            ],
            [
                468,
                382
            ]
        ]
    },
    {
        "class": "Left Lateral Canthus",
        "polygon": [
            [
                500,
                447
            ],
            [
                522,
                445
            ],
            [
                536,
                439
            ],
            [
                511,
                436
            ],
            [
                495,
                442
            ]
        ]
    },
    {
        "class": "Left Medial Canthus",
        "polygon": [
            [
                493,
                435
            ],
            [
                474,
                430
            ],
            [
                456,
                426
            ],
            [
                464,
                441
            ],
            [
                488,
                443
            ]
        ]
    },
    {
        "class": "Right Medial Canthus",
        "polygon": [
            [
                301,
                442
            ],
            [
                314,
                436
            ],
            [
                340,
                426
            ],
            [
                321,
                426
            ],
            [
                301,
                433
            ]
        ]
    },
    {
        "class": "Right Lateral Canthus",
        "polygon": [
            [
                281,
                442
            ],
            [
                298,
                443
            ],
            [
                297,
                430
            ],
            [
                278,
                434
            ],
            [
                260,
                430
            ],
            [
                259,
                437
            ]
        ]
    },
    {
        "class": "Upper Cheek",
        "polygon": [
            [
                342,
                437
            ],
            [
                338,
                485
            ],
            [
                301,
                493
            ],
            [
                264,
                493
            ],
            [
                239,
                473
            ],
            [
                243,
                451
            ],
            [
                275,
                456
            ],
            [
                311,
                446
            ]
        ]
    },
    {
        "class": "Upper Cheek",
        "polygon": [
            [
                460,
                445
            ],
            [
                493,
                458
            ],
            [
                532,
                452
            ],
            [
                553,
                500
            ],
            [
                514,
                499
            ],
            [
                470,
                492
            ],
            [
                453,
                470
            ]
        ]
    },
    {
        "class": "Lower Cheek",
        "polygon": [
            [
                327,
                496
            ],
            [
                299,
                501
            ],
            [
                280,
                503
            ],
            [
                247,
                495
            ],
            [
                250,
                522
            ],
            [
                282,
                526
            ],
            [
                319,
                517
            ]
        ]
    },
    {
        "class": "Lower Cheek",
        "polygon": [
            [
                468,
                501
            ],
            [
                499,
                502
            ],
            [
                533,
                506
            ],
            [
                534,
                525
            ],
            [
                499,
                536
            ],
            [
                472,
                527
            ]
        ]
    },
    {
        "class": "Border(lip region)",
        "polygon": [
            [
                344,
                552
            ],
            [
                384,
                543
            ],
            [
                411,
                543
            ],
            [
                456,
                554
            ],
            [
                437,
                583
            ],
            [
                394,
                595
            ],
            [
                355,
                578
            ]
        ]
    },
    {
        "class": "Mental region(chin)",
        "polygon": [
            [
                302,
                594
            ],
            [
                305,
                616
            ],
            [
                315,
                650
            ],
            [
                364,
                658
            ],
            [
                424,
                656
            ],
            [
                468,
                600
            ],
            [
                380,
                606
            ],
            [
                327,
                597
            ]
        ]
    }
]